pep_talk/__init__.py
pep_talk/main.py
pep_talk/pep_parts.py
pep_talk-0.0.2.dist-info/LICENSE
pep_talk-0.0.2.dist-info/METADATA
pep_talk-0.0.2.dist-info/WHEEL
pep_talk-0.0.2.dist-info/entry_points.txt
pep_talk-0.0.2.dist-info/top_level.txt
pep_talk-0.0.2.dist-info/RECORD
