Metadata-Version: 2.1
Name: pep-talk
Version: 0.0.2
Summary: Get a little bit of a boost today.
Home-page: https://github.com/chrishannam/pep-talk
Author: Chris Hannam
Author-email: ch@chrishannam.co.uk
License: UNKNOWN
Platform: UNKNOWN
Classifier: Programming Language :: Python :: 3
Classifier: License :: OSI Approved :: Apache Software License
Classifier: Operating System :: OS Independent
License-File: LICENSE
Requires-Dist: colored
